{
  "project_info": {
    "project_number": "117344344091",
    "project_id": "teamify-b6419",
    "storage_bucket": "teamify-b6419.firebasestorage.app"
  },
  "client": [
    {
      "client_info": {
        "mobilesdk_app_id": "1:117344344091:android:a6b30d0d580cf0d1cd00be",
        "android_client_info": {
          "package_name": "com.example.teamify"
        }
      },
      "oauth_client": [],
      "api_key": [
        {
          "current_key": "AIzaSyB39JUQiXvbpsKvmtIJUjAjrBKQZ0bKfDk"
        }
      ],
      "services": {
        "appinvite_service": {
          "other_platform_oauth_client": []
        }
      }
    }
  ],
  "configuration_version": "1"
}